helmstack.py
helmstack-1.9.0.dist-info/METADATA
helmstack-1.9.0.dist-info/WHEEL
helmstack-1.9.0.dist-info/entry_points.txt
helmstack-1.9.0.dist-info/top_level.txt
helmstack-1.9.0.dist-info/RECORD
