Metadata-Version: 2.1
Name: helmstack
Version: 1.9.0
Summary: See https://github.com/tonsV2/helmstack
Home-page: UNKNOWN
License: UNKNOWN
Platform: UNKNOWN
Requires-Python: >=3
Requires-Dist: click
Requires-Dist: ruamel.yaml
